<paquet
	prefix="courtcircuit"
	categorie="outil"
	version="2.4.0"
	etat="stable"
	compatibilite="[2.1.0;3.0.*]"
	logo="icon/courtcircuit-128.png"
	documentation="http://www.spip-contrib.net/?article3831"
>	

	<nom>Court-circuit</nom>
	<!-- Acc&#232;s direct aux articles -->

	<auteur lien="http://romy.tetue.net">romy.tetue.net</auteur>
	<auteur lien="http://www.spip-contrib.net/Joseph">Joseph</auteur>

	<pipeline nom="styliser" inclure="courtcircuit_pipelines.php" />
	<pipeline nom="ieconfig_metas" inclure="courtcircuit_ieconfig_metas.php" />

	<utilise nom="Z" />
	<utilise nom="compositions" />

	<menu nom="courtcircuit21" titre="courtcircuit:courtcircuit" parent="menu_squelette" icone="images/courtcircuit-16.png" action="configurer_courtcircuit" />
</paquet>