<composant>
  <!-- Nom du composant -->
  <nom>Recherche</nom>

  <!-- Auteur du composant -->
  <auteur>Daniel FAIVRE &copy; 2008-2015 - licence GPL</auteur>
  <version>1.0.1</version>
  <necessite id='acs' version='[0.8.8;]' />
  <group>nav</group>

  <param>
    <nom>preview</nom>
    <valeur>100</valeur>
  </param>

  <variable>
    <nom>TitreFond</nom>
    <type>color</type>
  </variable>
  <variable>
    <nom>TitreFondImage</nom>
    <type>img</type>
    <chemin>trame</chemin>
    <label>non</label>
  </variable>
  <variable>
    <nom>Bord</nom>
    <type>bord</type>
  </variable>
  <variable>
    <nom>BordRond</nom>
    <type>text</type>
  </variable>
  <variable>
    <nom>Fond</nom>
    <type>color</type>
  </variable>
  <variable>
    <nom>Label</nom>
    <type>choix</type>
    <option>oui</option>
    <option>non</option>
    <valeur>oui</valeur>
  </variable>
	<variable>
    <nom>Shadow</nom>
    <type>color</type>
  </variable>
  <variable>
    <nom>ShadowSize</nom>
    <type>text</type>
  </variable>
  <variable>
  	<nom>ShadowBlur</nom>
    <type>text</type>
  </variable>

  <variable>
    <nom>Input</nom>
    <type>color</type>
  </variable>
  <variable>
    <nom>InputBord</nom>
    <type>bord</type>
  </variable>
  <variable>
    <nom>Button</nom>
    <type>img</type>
    <chemin>recherche</chemin>
  </variable>
</composant>