<traduction module="couteau" gestionnaire="salvatore" url="http://trad.spip.org" source="svn://zone.spip.org/spip-zone/_plugins_/couteau_suisse/lang/" reference="fr">
	<langue code="ar">
		<traducteur nom="George" />
	</langue>
	<langue code="ast" />
	<langue code="br" />
	<langue code="ca">
		<traducteur nom="merce" />
	</langue>
	<langue code="de">
		<traducteur nom="klaus++" />
	</langue>
	<langue code="en">
		<traducteur nom="sQuonk" />
		<traducteur nom="George" />
	</langue>
	<langue code="es" />
	<langue code="fa">
		<traducteur nom="Davood Hossein" />
	</langue>
	<langue code="fr" />
	<langue code="fr_tu">
		<traducteur nom="beatnick" />
	</langue>
	<langue code="gl" />
	<langue code="it" />
	<langue code="nl">
		<traducteur nom="mpossoz" />
	</langue>
	<langue code="pt_br">
		<traducteur nom="Ricardo Porto" />
	</langue>
	<langue code="ro" />
	<langue code="sk">
		<traducteur nom="jaro" />
	</langue>
	<langue code="tr" />
</traduction>
