<traduction module="album" gestionnaire="salvatore" url="http://trad.spip.net" source="svn://zone.spip.org/spip-zone/_plugins_/albums/trunk/lang/" reference="fr">
	<langue code="en" url="http://trad.spip.net/tradlang_module/album?lang_cible=en" total="107" traduits="91" relire="0" modifs="6" nouveaux="10" pourcent="85.05">
		<traducteur nom="Benitron" lien="http://trad.spip.net/auteur/benitron" />
		<traducteur nom="Gilles" lien="http://trad.spip.net/auteur/gilles" />
		<traducteur nom="Hanjo" lien="http://trad.spip.net/auteur/hanjo" />
		<traducteur nom="SuperYMS" lien="http://trad.spip.net/auteur/superyms" />
		<traducteur nom="tcharlss" lien="http://trad.spip.net/auteur/drbouvierleduc" />
	</langue>
	<langue code="es" url="http://trad.spip.net/tradlang_module/album?lang_cible=es" total="107" traduits="69" relire="21" modifs="7" nouveaux="10" pourcent="64.49">
		<traducteur nom="Raquel S. Bujaldón" lien="http://trad.spip.net/auteur/raquel-s-bujaldon" />
		<traducteur nom="tcharlss" lien="http://trad.spip.net/auteur/drbouvierleduc" />
	</langue>
	<langue code="fr" url="http://trad.spip.net/tradlang_module/album?lang_cible=fr" total="107" traduits="107" relire="0" modifs="0" nouveaux="0" pourcent="100.00">
	</langue>
	<langue code="nl" url="http://trad.spip.net/tradlang_module/album?lang_cible=nl" total="107" traduits="96" relire="0" modifs="3" nouveaux="8" pourcent="89.72">
		<traducteur nom="Hanjo" lien="http://trad.spip.net/auteur/hanjo" />
	</langue>
</traduction>
