<paquet
	prefix="continents"
	categorie="outil"
	version="1.1.1"
	etat="stable"
	compatibilite="[3.0.10;3.2.*]"
	logo="prive/themes/spip/images/continents-64.png"
	documentation=""
	schema="1.1.0"
>

	<nom>Continents</nom>

	<auteur lien='http://websimple.be/'>Rainer M&#252;ller</auteur>

	<licence>GNU/GPL</licence>

	<necessite nom="pays" compatibilite="[3.2.0;]" />

	<pipeline nom="declarer_tables_interfaces" inclure="base/continents.php" />
	<pipeline nom="declarer_tables_principales" inclure="base/continents.php" />

</paquet>